[ 
    {"name" : "عبدالرحمن الجابري", "strength" : 2, "pose": "D", "movement" : 3  } ,
    {"name" : "حامد", "strength" : 3, "pose": "D", "movement" : 3  } ,
    {"name" : "سعد", "strength" : 3, "pose": "M", "movement" : 3  } ,
    {"name" : "ناصر", "strength" : 5, "pose": "M", "movement" : 4 } ,
    {"name" : "الحارث", "strength" : 3, "pose": "D", "movement" : 3  } ,
    {"name" : "خليفة", "strength" : 3, "pose": "M", "movement" : 3  } ,
    {"name" : "عبدالله وحيد", "strength" : 1, "pose": "F", "movement" : 1  } ,
    {"name" : "حسن الشروقي", "strength" : 3, "pose": "D", "movement" : 3  } ,
    {"name" : "الشروقي", "strength" : 2, "pose": "D", "movement" : 3  } ,
    {"name" : "المران", "strength" : 3, "pose": "M", "movement" : 3  } ,
    {"name" : "صباح", "strength" : 2, "pose": "M", "movement" : 2  } ,
    {"name" : "خالد", "strength" : 4, "pose": "M", "movement" : 3  } ,
    {"name" : "فواز", "strength" : 5, "pose": "M", "movement" : 5  } ,
    {"name" : "السلم", "strength" : 2, "pose": "F", "movement" : 1  } ,
    {"name" : "عبدالله الذوادي ", "strength" : 2, "pose": "M", "movement" : 3  } ,
    {"name" : "سعود الجار ", "strength" : 3, "pose": "D", "movement" : 4  } ,
    {"name" : "العطاوي  ", "strength" : 3, "pose": "M", "movement" : 3  } ,
    {"name" : "خالد بوالفتح ", "strength" : 4, "pose": "M", "movement" : 3  } ,
     {"name" : " علي بوعلي", "strength" : 3, "pose": "D", "movement" : 2  } ,
    {"name" : "عبدالرحمن أحمد ", "strength" : 4, "pose": "M", "movement" : 5  },
     {"name" : "عبدالله س الجابري ", "strength" : 2, "pose": "M", "movement" : 2  },
    {"name" : " محمد المحمود ", "strength" : 2, "pose": "D", "movement" : 3  },
    {"name" : " خليل", "strength" : 3, "pose": "M", "movement" : 3  }
    
    ]
